.gitignore
LICENSE.txt
README
setup.py
django_memcached/__init__.py
django_memcached/models.py
django_memcached/urls.py
django_memcached/util.py
django_memcached/views.py
django_memcached.egg-info/PKG-INFO
django_memcached.egg-info/SOURCES.txt
django_memcached.egg-info/dependency_links.txt
django_memcached.egg-info/not-zip-safe
django_memcached.egg-info/requires.txt
django_memcached.egg-info/top_level.txt
django_memcached/templates/memcached/server_list.html
django_memcached/templates/memcached/server_status.html