Metadata-Version: 1.0
Name: django-memcached
Version: 0.1.2
Summary: django-memcached is a very simple reusable app which does one simple thing: shows you statistics about your currently running memcached instances
Home-page: http://github.com/ericflo/django-memcached/tree/master
Author: Eric Florenzano
Author-email: floguy@gmail.com
License: BSD
Keywords: memcached,django
Platform: UNKNOWN
Classifier: Programming Language :: Python
Classifier: Topic :: Software Development :: Libraries :: Python Modules
Classifier: Framework :: Django
Classifier: Environment :: Web Environment
